HISTORY.rst
LICENSE.rst
MANIFEST.in
README.rst
crawly.py
setup.py
crawly.egg-info/PKG-INFO
crawly.egg-info/SOURCES.txt
crawly.egg-info/dependency_links.txt
crawly.egg-info/requires.txt
crawly.egg-info/top_level.txt
crawly.egg-info/zip-safe